emfile/__init__.py
emfile/_version.py
emfile/read.py
emfile/specs.py
emfile/write.py
emfile-0.3.0.dist-info/LICENSE
emfile-0.3.0.dist-info/METADATA
emfile-0.3.0.dist-info/WHEEL
emfile-0.3.0.dist-info/top_level.txt
emfile-0.3.0.dist-info/RECORD
